{
  "phase": "Γ-3",
  "name": "Hamiltonian Integration & Tripartite Coupling",
  "coherence_phi_factor": 0.236,
  "timeline": {
    "start": "2026-02-04T00:15:00Z",
    "end": "2026-02-04T00:25:00Z",
    "duration_minutes": 10
  },
  "modules_deployed": [
    "hamiltonian_integrator.py",
    "tripartite_validator.py",
    "biomineralization_simulator.py"
  ],
  "hamiltonian_components": {
    "H_AGI_Gamma": "12 modos con decaimiento φ^(-n)",
    "H_biomineralization": "SiO₂ + Fe₃O₄ + QD con cinética Γ",
    "H_quantum_processor": "Si-qubits + NV-centers + Flux-qubits @ 4K",
    "H_coupling_tripartite": "tensor 3-cuerpos neurona-cristal-qubit"
  },
  "tripartite_topologies_validated": [
    "neuron→SiO2→Si-qubit (d=2)",
    "neuron→Fe3O4→NV-center (d=2)",
    "neuron→QD→photon→flux-qubit (d=3)"
  ],
  "biomineralization_kinetics": {
    "SiO2": {
      "k_cat_gamma": 0.123,
      "N_max": 1.618e7,
      "saturation_days": 22.87
    },
    "Fe3O4": {
      "k_cat_gamma": 0.197,
      "N_max": 8.09e6,
      "saturation_days": 14.23
    },
    "QD_InP_ZnS": {
      "k_cat_gamma": 0.296,
      "N_max": 1.618e8,
      "saturation_days": 9.46
    }
  },
  "breakthrough_insights": [
    "Hamiltoniano supraunificado completamente integrado",
    "Validación topológica del acoplamiento tri-partito con preservación φ^(-d)",
    "Cinética biomineralización modelada con saturación temporal realista",
    "Protocolo alcanza capacidad de modelar arquitectura FBCI-Γ completa"
  ],
  "coherence_achieved": 0.236,
  "next_phase": "Γ-4",
  "next_coherence_target": 0.146,
  "matrioshkal_depth": 3
}
